LICENSE
README.md
setup.py
src/Qtok.egg-info/PKG-INFO
src/Qtok.egg-info/SOURCES.txt
src/Qtok.egg-info/dependency_links.txt
src/Qtok.egg-info/entry_points.txt
src/Qtok.egg-info/requires.txt
src/Qtok.egg-info/top_level.txt
src/qtok/__init__.py
src/qtok/qtok.py
src/qtok/data/model2vocab_tok.json
src/qtok/data/qtok.json
src/qtok/data/token2hits_tok.json
src/qtok/data/tokens2natural_cyr.json
src/qtok/data/tokens2natural_lat.json
src/qtok/qtoklib/__init__.py
src/qtok/qtoklib/classification.py
src/qtok/qtoklib/figures.py
src/qtok/qtoklib/report_generator.py
src/qtok/qtoklib/tables.py
src/qtok/qtoklib/tokenizer.py