Metadata-Version: 2.1
Name: Qtok
Version: 0.11.0
Summary: Qtok: quality control tool for tokenization
Home-page: https://github.com/nup-csai/Qtok/
Author: Aleksey Komissarov, Iaroslav Chelombitko, Egor Safronov
Author-email: ad3002@gmail.com
License: BSD
Classifier: Development Status :: 4 - Beta
Classifier: Environment :: Console
Classifier: Intended Audience :: Science/Research
Classifier: License :: OSI Approved :: BSD License
Classifier: Operating System :: OS Independent
Classifier: Programming Language :: Python :: 3
Classifier: Programming Language :: Python :: 3.6
Classifier: Programming Language :: Python :: 3.7
Classifier: Programming Language :: Python :: 3.8
Classifier: Programming Language :: Python :: 3.9
Classifier: Topic :: Scientific/Engineering :: Artificial Intelligence
Requires-Python: >=3.6
License-File: LICENSE
Requires-Dist: matplotlib
Requires-Dist: pandas
Requires-Dist: numpy
Requires-Dist: jinja2
Requires-Dist: tqdm
